finestock/__init__.py
finestock/api_fcatory.py
finestock/path.py
finestock/comm/__init__.py
finestock/comm/api.py
finestock/comm/api_interface.py
finestock/ebest/__init__.py
finestock/ebest/ebest.py
finestock/kis/__init__.py
finestock/kis/kis.py
finestock/kis/kis_v.py
finestock/ls/__init__.py
finestock/ls/ls.py
finestock/ls/ls_v.py
finestock/model/__init__.py
finestock/model/flag.py
finestock/model/price.py
finestock/model/trade.py
finestock-0.5.3.1.dist-info/METADATA
finestock-0.5.3.1.dist-info/WHEEL
finestock-0.5.3.1.dist-info/top_level.txt
finestock-0.5.3.1.dist-info/RECORD
