Metadata-Version: 2.4
Name: finestock
Version: 0.5.3.1
Summary: Korean Stock OpenAPI Package(EBest, KIS, LS) creation written by alshin
Home-page: https://github.com/shinalok/finestock
Author: A.Lok, Shin
Author-email: shinalok357@gmail.com
Keywords: ebest,kis,ls,openapi,stock,kr
Classifier: Programming Language :: Python :: 3.6
Classifier: Programming Language :: Python :: 3.7
Classifier: Programming Language :: Python :: 3.8
Classifier: Programming Language :: Python :: 3.9
Requires-Python: >=3.6
Requires-Dist: websockets
Requires-Dist: asyncio
Requires-Dist: requests
Requires-Dist: loguru
Dynamic: author
Dynamic: author-email
Dynamic: classifier
Dynamic: home-page
Dynamic: keywords
Dynamic: requires-dist
Dynamic: requires-python
Dynamic: summary
